toolbox/__init__.py
toolbox/cli.py
toolbox/common/calendar.py
toolbox/common/exceptions.py
toolbox/common/file.py
toolbox/common/output.py
toolbox/common/work.py
toolbox/scripts.py
toolbox/sets/business/__init__.py
toolbox/sets/business/__version__.py
toolbox/sets/business/cli.py
toolbox/sets/dw/__init__.py
toolbox/sets/dw/__version__.py
toolbox/sets/dw/cli.py
toolbox/sets/dw/download.py
toolbox/sets/hash/__init__.py
toolbox/sets/hash/__version__.py
toolbox/sets/hash/cli.py
toolbox/sets/hash/hash_algoritms_enum.py
toolbox/sets/pdf/__init__.py
toolbox/sets/pdf/__version__.py
toolbox/sets/pdf/cli.py
toolbox/sets/pdf/converter.py
atelier_toolbox-1.1.1.dist-info/LICENSE
atelier_toolbox-1.1.1.dist-info/METADATA
atelier_toolbox-1.1.1.dist-info/WHEEL
atelier_toolbox-1.1.1.dist-info/entry_points.txt
atelier_toolbox-1.1.1.dist-info/RECORD
