Metadata-Version: 2.1
Name: atelier-toolbox
Version: 1.1.1
Summary: Tools for various automations 🧰
Home-page: https://github.com/mihaichris/atelier-toolbox
License: MIT
Keywords: toolbox,automation,poetry
Author: Mihai
Requires-Python: >=3.10,<4.0
Classifier: License :: OSI Approved :: MIT License
Classifier: Programming Language :: Python :: 3
Classifier: Programming Language :: Python :: 3.10
Classifier: Programming Language :: Python :: 3.11
Classifier: Programming Language :: Python :: 3.12
Requires-Dist: click (>=8.1.3,<9.0.0)
Requires-Dist: pylint (>=2.15.5,<3.0.0)
Requires-Dist: pytest (>=7.2,<8.0)
Requires-Dist: rich (>=12.6.0,<13.0.0)
Requires-Dist: tomli (>=2.0.1,<3.0.0)
Requires-Dist: typer[all] (>=0.6.1,<0.7.0)
Project-URL: Repository, https://github.com/mihaichris/atelier-toolbox
